skillsnetwork_jupyter_extension/__init__.py
skillsnetwork_jupyter_extension/_version.py
skillsnetwork_jupyter_extension/handlers.py
skillsnetwork_jupyter_extension-2.3.1.data/data/etc/jupyter/jupyter_server_config.d/skillsnetwork_jupyter_extension.json
skillsnetwork_jupyter_extension-2.3.1.data/data/share/jupyter/labextensions/skillsnetwork_jupyter_extension/package.json
skillsnetwork_jupyter_extension-2.3.1.data/data/share/jupyter/labextensions/skillsnetwork_jupyter_extension/schemas/skillsnetwork_jupyter_extension/package.json.orig
skillsnetwork_jupyter_extension-2.3.1.data/data/share/jupyter/labextensions/skillsnetwork_jupyter_extension/schemas/skillsnetwork_jupyter_extension/toolbar.json
skillsnetwork_jupyter_extension-2.3.1.data/data/share/jupyter/labextensions/skillsnetwork_jupyter_extension/static/496.b3c32afd949d9a1b151d.js
skillsnetwork_jupyter_extension-2.3.1.data/data/share/jupyter/labextensions/skillsnetwork_jupyter_extension/static/636.605077303a876f967661.js
skillsnetwork_jupyter_extension-2.3.1.data/data/share/jupyter/labextensions/skillsnetwork_jupyter_extension/static/648.64f5e2269a630e211878.js
skillsnetwork_jupyter_extension-2.3.1.data/data/share/jupyter/labextensions/skillsnetwork_jupyter_extension/static/736.7b5f76df818add15df8b.js
skillsnetwork_jupyter_extension-2.3.1.data/data/share/jupyter/labextensions/skillsnetwork_jupyter_extension/static/944.dddd8170d5a83693b53a.js
skillsnetwork_jupyter_extension-2.3.1.data/data/share/jupyter/labextensions/skillsnetwork_jupyter_extension/static/956.fb9e1ea921bfd97d8c96.js
skillsnetwork_jupyter_extension-2.3.1.data/data/share/jupyter/labextensions/skillsnetwork_jupyter_extension/static/remoteEntry.fc9cbf978ae25d1a7c1a.js
skillsnetwork_jupyter_extension-2.3.1.data/data/share/jupyter/labextensions/skillsnetwork_jupyter_extension/static/style.js
skillsnetwork_jupyter_extension-2.3.1.data/data/share/jupyter/labextensions/skillsnetwork_jupyter_extension/static/third-party-licenses.json
skillsnetwork_jupyter_extension-2.3.1.dist-info/METADATA
skillsnetwork_jupyter_extension-2.3.1.dist-info/WHEEL
skillsnetwork_jupyter_extension-2.3.1.dist-info/licenses/LICENSE
skillsnetwork_jupyter_extension-2.3.1.dist-info/RECORD
