Metadata-Version: 2.3
Name: skillsnetwork_jupyter_extension
Version: 2.3.1
Dynamic: Keywords
Summary: JupterLab/JupyerLite extension for Skills Network Labs
Project-URL: Homepage, https://github.com/ibm-skills-network/skillsnetwork-jupyter-extension
Project-URL: Bug Tracker, https://github.com/ibm-skills-network/skillsnetwork-jupyter-extension/issues
Project-URL: Repository, https://github.com/ibm-skills-network/skillsnetwork-jupyter-extension.git
Author-email: IBM Skills Network <skills.network@ibm.com>
License:                                  Apache License
License-File: LICENSE
Classifier: Framework :: Jupyter
Classifier: Framework :: Jupyter :: JupyterLab
Classifier: Framework :: Jupyter :: JupyterLab :: 4
Classifier: Framework :: Jupyter :: JupyterLab :: Extensions
Classifier: Framework :: Jupyter :: JupyterLab :: Extensions :: Prebuilt
Classifier: License :: OSI Approved :: BSD License
Classifier: Programming Language :: Python
Classifier: Programming Language :: Python :: 3
Classifier: Programming Language :: Python :: 3.8
Classifier: Programming Language :: Python :: 3.9
Classifier: Programming Language :: Python :: 3.10
Classifier: Programming Language :: Python :: 3.11
Classifier: Programming Language :: Python :: 3.12
Requires-Python: >=3.8
Requires-Dist: jupyter-server<3,>=2.0.1
